vitaoptimum/__init__.py
vitaoptimum/base.py
vitaoptimum/logo64.png
vitaoptimum/plot.py
vitaoptimum/result.py
vitaoptimum/vo/__init__.py
vitaoptimum/vo/bcs.py
vitaoptimum/vo/bus.py
vitaoptimum/vo/ccs.py
vitaoptimum/vo/constrained.py
vitaoptimum/vo/cus.py
vitaoptimum/vo/ics.py
vitaoptimum/vo/ius.py
vitaoptimum/vo/mcs.py
vitaoptimum/vo/mixed.py
vitaoptimum/vo/mus.py
vitaoptimum/vo/pcs.py
vitaoptimum/vo/pus.py
vitaoptimum/vo/unconstrained.py
vitaoptimum/voplus/__init__.py
vitaoptimum/voplus/bcs.py
vitaoptimum/voplus/bus.py
vitaoptimum/voplus/ccs.py
vitaoptimum/voplus/constrained.py
vitaoptimum/voplus/cus.py
vitaoptimum/voplus/ics.py
vitaoptimum/voplus/ius.py
vitaoptimum/voplus/mcs.py
vitaoptimum/voplus/mixed.py
vitaoptimum/voplus/mus.py
vitaoptimum/voplus/pcs.py
vitaoptimum/voplus/pus.py
vitaoptimum/voplus/unconstrained.py
vitaoptimum-1.5.8.dist-info/DESCRIPTION.rst
vitaoptimum-1.5.8.dist-info/METADATA
vitaoptimum-1.5.8.dist-info/RECORD
vitaoptimum-1.5.8.dist-info/WHEEL
vitaoptimum-1.5.8.dist-info/metadata.json
vitaoptimum-1.5.8.dist-info/top_level.txt
