Metadata-Version: 2.0
Name: vitaoptimum
Version: 1.5.8
Summary: Global Optimum Search Algorithms Python Interface Package
Home-page: http://skyworkflows.com
Author: Sky Workflows
Author-email: vo@skyworkflows.com
License: UNKNOWN
Keywords: algorithms optimization global metaheuristic evolutionary genetic evolution swarm
Platform: UNKNOWN
Classifier: Programming Language :: Python :: 3
Classifier: License :: OSI Approved :: MIT License
Classifier: Operating System :: OS Independent
Requires-Dist: numpy
